odoo8_addon_account_invoice_reorder_lines-8.0.1.0.0.99.dev18-py2.7-nspkg.pth
odoo8_addon_account_invoice_reorder_lines-8.0.1.0.0.99.dev18.dist-info/METADATA
odoo8_addon_account_invoice_reorder_lines-8.0.1.0.0.99.dev18.dist-info/RECORD
odoo8_addon_account_invoice_reorder_lines-8.0.1.0.0.99.dev18.dist-info/WHEEL
odoo8_addon_account_invoice_reorder_lines-8.0.1.0.0.99.dev18.dist-info/namespace_packages.txt
odoo8_addon_account_invoice_reorder_lines-8.0.1.0.0.99.dev18.dist-info/top_level.txt
odoo_addons/account_invoice_reorder_lines/README.rst
odoo_addons/account_invoice_reorder_lines/__init__.py
odoo_addons/account_invoice_reorder_lines/__openerp__.py
odoo_addons/account_invoice_reorder_lines/invoice.py
odoo_addons/account_invoice_reorder_lines/invoice_view.xml
odoo_addons/account_invoice_reorder_lines/i18n/account_invoice_reorder_lines.pot
odoo_addons/account_invoice_reorder_lines/i18n/ca.po
odoo_addons/account_invoice_reorder_lines/i18n/de.po
odoo_addons/account_invoice_reorder_lines/i18n/es.po
odoo_addons/account_invoice_reorder_lines/i18n/es_MX.po
odoo_addons/account_invoice_reorder_lines/i18n/fr.po
odoo_addons/account_invoice_reorder_lines/i18n/fr_CH.po
odoo_addons/account_invoice_reorder_lines/i18n/hr.po
odoo_addons/account_invoice_reorder_lines/i18n/it.po
odoo_addons/account_invoice_reorder_lines/i18n/nl_NL.po
odoo_addons/account_invoice_reorder_lines/i18n/pt_BR.po
odoo_addons/account_invoice_reorder_lines/i18n/pt_PT.po
odoo_addons/account_invoice_reorder_lines/i18n/sl.po
odoo_addons/account_invoice_reorder_lines/i18n/tr.po
odoo_addons/account_invoice_reorder_lines/i18n/tr_TR.po
odoo_addons/account_invoice_reorder_lines/static/description/icon.png
