Metadata-Version: 2.1
Name: odoo8-addon-account-invoice-reorder-lines
Version: 8.0.1.0.0.99.dev18
Summary: Provide a new field on the invoice line form, allowing to manage the lines
Requires-Dist: odoo (<9.0a,>=8.0a)
